kamuidrome-0.8.3.dist-info/METADATA
kamuidrome-0.8.3.dist-info/WHEEL
kamuidrome-0.8.3.dist-info/entry_points.txt
kamuidrome-0.8.3.dist-info/licenses/LICENCE
kamuidrome/__init__.py
kamuidrome/cache.py
kamuidrome/cli/__init__.py
kamuidrome/cli/__main__.py
kamuidrome/cli/add.py
kamuidrome/cli/init.py
kamuidrome/cli/list.py
kamuidrome/cli/update.py
kamuidrome/exc.py
kamuidrome/meta.py
kamuidrome/modrinth/__init__.py
kamuidrome/modrinth/client.py
kamuidrome/modrinth/models.py
kamuidrome/modrinth/mrpack.py
kamuidrome/modrinth/utils.py
kamuidrome/pack.py
kamuidrome/prism.py
kamuidrome/py.typed
kamuidrome/retry.py
kamuidrome-0.8.3.dist-info/RECORD
