Metadata-Version: 2.1
Name: kamuidrome
Version: 0.8.3
Summary: Modern Minecraft modpack builder
Author-Email: Lura Skye <fuyukai@proton.me>
License: GPL-3.0-or-later
Classifier: Development Status :: 4 - Beta
Classifier: Environment :: Console
Classifier: Topic :: Games/Entertainment
Classifier: License :: OSI Approved :: GNU General Public License v3 or later (GPLv3+)
Requires-Python: >=3.12
Requires-Dist: httpx>=0.28.1
Requires-Dist: attrs>=24.3.0
Requires-Dist: tomlkit>=0.13.2
Requires-Dist: rich>=13.9.4
Requires-Dist: platformdirs>=4.3.6
Requires-Dist: more-itertools>=10.5.0
Requires-Dist: cattrs>=24.1.2
Requires-Dist: whenever>=0.8.0
